{"version": "0.2.0-beta.6", "img_width": 1100, "img_height": 1600, "blocks": [{"box": [932, 65, 1006, 203], "vertical": true, "font_size": 22, "lines_coords": [[[982.0, 67.0], [1004.0, 67.0], [1004.0, 181.0], [982.0, 181.0]], [[956.0, 67.0], [978.0, 67.0], [978.0, 203.0], [956.0, 203.0]]], "lines": ["．．．もすもす", "南条ですけど"]}, {"box": [777, 130, 834, 344], "vertical": true, "font_size": 22, "lines_coords": [[[810.0, 131.0], [832.0, 131.0], [832.0, 332.0], [810.0, 332.0]], [[778.0, 131.0], [800.0, 131.0], [800.0, 337.0], [778.0, 337.0]]], "lines": ["．．．こんな気持ちに", "なるのか嫌だから"]}, {"box": [603, 51, 681, 236], "vertical": true, "font_size": 20, "lines_coords": [[[657.0, 54.0], [678.0, 54.0], [678.0, 212.0], [657.0, 212.0]], [[629.0, 53.0], [651.0, 53.0], [651.0, 221.0], [629.0, 221.0]], [[603.0, 51.0], [623.0, 51.0], [623.0, 185.0], [603.0, 185.0]], [[604.0, 182.0], [621.0, 182.0], [621.0, 232.0], [604.0, 232.0]]], "lines": ["もう３０分くらい", "待ってんだけど。", "．．．どうしたー", "ーっ"]}, {"box": [440, 75, 546, 117], "vertical": false, "font_size": 22, "lines_coords": [[[445.0, 75.0], [546.0, 95.0], [542.0, 117.0], [440.0, 96.0]]], "lines": ["クオンサイセイチ、"]}, {"box": [335, 68, 390, 253], "vertical": true, "font_size": 26, "lines_coords": [[[364.0, 70.0], [390.0, 70.0], [387.0, 231.0], [360.0, 231.0]], [[339.0, 68.0], [364.0, 68.0], [360.0, 196.0], [335.0, 196.0]]], "lines": ["．．．駅、混んでき", "ちゃったよ！"]}, {"box": [190, 129, 284, 282], "vertical": true, "font_size": 28, "lines_coords": [[[248.0, 131.0], [284.0, 131.0], [284.0, 212.0], [248.0, 212.0]], [[220.0, 131.0], [246.0, 131.0], [246.0, 282.0], [220.0, 282.0]], [[190.0, 131.0], [212.0, 131.0], [212.0, 264.0], [190.0, 264.0]]], "lines": ["一人で", "生きていくと", "決めたのに。"]}, {"box": [139, 329, 191, 468], "vertical": true, "font_size": 22, "lines_coords": [[[168.0, 331.0], [190.0, 331.0], [190.0, 445.0], [168.0, 445.0]], [[140.0, 329.0], [162.0, 329.0], [160.0, 468.0], [139.0, 468.0]]], "lines": ["．．．そろそろ", "帰りますわ．．．"]}, {"box": [390, 562, 418, 590], "vertical": false, "font_size": 28, "lines_coords": [[[390.0, 562.0], [418.0, 562.0], [418.0, 590.0], [390.0, 590.0]]], "lines": ["あ"]}, {"box": [295, 686, 346, 740], "vertical": true, "font_size": 27, "lines_coords": [[[318.0, 687.0], [346.0, 687.0], [346.0, 715.0], [318.0, 715.0]], [[295.0, 712.0], [321.0, 712.0], [321.0, 740.0], [295.0, 740.0]]], "lines": ["あ", "あ"]}, {"box": [356, 981, 382, 1009], "vertical": true, "font_size": 26, "lines_coords": [[[356.0, 981.0], [382.0, 981.0], [382.0, 1009.0], [356.0, 1009.0]]], "lines": ["あ"]}, {"box": [260, 1045, 320, 1115], "vertical": true, "font_size": 30, "lines_coords": [[[292.0, 1048.0], [320.0, 1048.0], [320.0, 1075.0], [292.0, 1075.0]], [[260.0, 1060.0], [292.0, 1060.0], [292.0, 1115.0], [260.0, 1115.0]]], "lines": ["あ", "あん"]}, {"box": [593, 1343, 657, 1499], "vertical": true, "font_size": 28, "lines_coords": [[[632.0, 1346.0], [654.0, 1346.0], [654.0, 1495.0], [632.0, 1495.0]], [[593.0, 1343.0], [626.0, 1343.0], [626.0, 1432.0], [593.0, 1432.0]]], "lines": ["ちょっと油断", "したら、"]}, {"box": [409, 1346, 435, 1434], "vertical": true, "font_size": 26, "lines_coords": [[[409.0, 1346.0], [435.0, 1346.0], [435.0, 1432.0], [409.0, 1432.0]]], "lines": ["これだ。"]}]}