{"version": "0.1.7", "img_width": 1296, "img_height": 2008, "blocks": [{"box": [1066, 305, 1209, 464], "vertical": true, "font_size": 46, "lines_coords": [[[1160.0, 305.0], [1209.0, 305.0], [1209.0, 429.0], [1160.0, 429.0]], [[1107.0, 305.0], [1166.0, 305.0], [1166.0, 433.0], [1107.0, 433.0]], [[1070.0, 309.0], [1111.0, 309.0], [1107.0, 464.0], [1066.0, 464.0]]], "lines": ["うわっ", "なんか", "ついた！"]}, {"box": [1068, 309, 1208, 468], "vertical": true, "font_size": 140, "lines_coords": [[[1068.0, 309.0], [1208.0, 309.0], [1208.0, 468.0], [1068.0, 468.0]]], "lines": ["うわっなんかついた！"]}, {"box": [307, 113, 419, 209], "vertical": true, "font_size": 40, "lines_coords": [[[384.0, 115.0], [419.0, 115.0], [419.0, 205.0], [384.0, 205.0]], [[347.0, 113.0], [390.0, 113.0], [390.0, 209.0], [347.0, 209.0]], [[311.0, 113.0], [354.0, 115.0], [350.0, 205.0], [307.0, 203.0]]], "lines": ["うわっ", "ひでー", "こいつ"]}, {"box": [296, 386, 315, 475], "vertical": true, "font_size": 19, "lines_coords": [[[296.0, 386.0], [315.0, 386.0], [315.0, 475.0], [296.0, 475.0]]], "lines": ["．．．"]}, {"box": [1006, 516, 1053, 709], "vertical": true, "font_size": 47, "lines_coords": [[[1006.0, 516.0], [1053.0, 516.0], [1053.0, 709.0], [1006.0, 709.0]]], "lines": ["きったね！"]}, {"box": [1011, 517, 1045, 705], "vertical": true, "font_size": 46, "lines_coords": [[[1011.0, 517.0], [1045.0, 517.0], [1045.0, 705.0], [1011.0, 705.0]]], "lines": ["きったね！"]}, {"box": [1084, 868, 1254, 1088], "vertical": true, "font_size": 50, "lines_coords": [[[1197.0, 868.0], [1254.0, 868.0], [1254.0, 1007.0], [1197.0, 1007.0]], [[1141.0, 872.0], [1182.0, 872.0], [1182.0, 1088.0], [1141.0, 1088.0]], [[1084.0, 868.0], [1135.0, 868.0], [1135.0, 1005.0], [1084.0, 1005.0]]], "lines": ["なんだ", "も１コある", "じゃん"]}, {"box": [462, 857, 484, 926], "vertical": true, "font_size": 22, "lines_coords": [[[462.0, 857.0], [484.0, 857.0], [484.0, 926.0], [462.0, 926.0]]], "lines": ["．．．"]}, {"box": [54, 720, 82, 785], "vertical": true, "font_size": 28, "lines_coords": [[[54.0, 720.0], [82.0, 720.0], [82.0, 785.0], [54.0, 785.0]]], "lines": ["ん？"]}, {"box": [1119, 1500, 1168, 1629], "vertical": true, "font_size": 49, "lines_coords": [[[1119.0, 1500.0], [1168.0, 1500.0], [1168.0, 1629.0], [1119.0, 1629.0]]], "lines": ["うわっ"]}, {"box": [639, 1692, 748, 1866], "vertical": true, "font_size": 32, "lines_coords": [[[711.0, 1692.0], [748.0, 1692.0], [748.0, 1753.0], [711.0, 1753.0]], [[678.0, 1694.0], [711.0, 1694.0], [711.0, 1837.0], [678.0, 1837.0]], [[639.0, 1696.0], [664.0, 1696.0], [664.0, 1864.0], [639.0, 1864.0]]], "lines": ["ゲェ", "ショーヤぁ", "お前やりすぎ"]}, {"box": [443, 1615, 521, 1806], "vertical": true, "font_size": 34, "lines_coords": [[[486.0, 1615.0], [521.0, 1615.0], [521.0, 1745.0], [486.0, 1745.0]], [[447.0, 1617.0], [480.0, 1617.0], [476.0, 1806.0], [443.0, 1806.0]]], "lines": ["ちょっと", "やばくない？"]}, {"box": [88, 1731, 194, 1900], "vertical": true, "font_size": 31, "lines_coords": [[[156.0, 1731.0], [194.0, 1731.0], [194.0, 1821.0], [156.0, 1821.0]], [[125.0, 1733.0], [152.0, 1733.0], [156.0, 1900.0], [129.0, 1900.0]], [[88.0, 1735.0], [115.0, 1735.0], [115.0, 1870.0], [88.0, 1870.0]]], "lines": ["だから", "やめなよって", "言ったのに"]}]}