{"version": "0.2.0-beta.6", "img_width": 847, "img_height": 1200, "blocks": [{"box": [673, 168, 695, 276], "vertical": true, "font_size": 20, "lines_coords": [[[675.0, 168.0], [695.0, 168.0], [693.0, 276.0], [673.0, 276.0]]], "lines": ["．．．ごめんね。"]}, {"box": [584, 315, 599, 416], "vertical": true, "font_size": 15, "lines_coords": [[[584.0, 315.0], [599.0, 315.0], [599.0, 416.0], [584.0, 416.0]]], "lines": ["ＰＰＲＰＰＰ：："]}, {"box": [369, 532, 384, 633], "vertical": true, "font_size": 15, "lines_coords": [[[369.0, 533.0], [384.0, 533.0], [384.0, 632.0], [369.0, 632.0]]], "lines": ["ＰｐｐＰＰＰ：："]}, {"box": [179, 341, 198, 446], "vertical": true, "font_size": 16, "lines_coords": [[[179.0, 343.0], [195.0, 343.0], [195.0, 444.0], [179.0, 444.0]]], "lines": ["愛子ちゃん。"]}, {"box": [595, 727, 610, 829], "vertical": true, "font_size": 15, "lines_coords": [[[595.0, 727.0], [610.0, 727.0], [610.0, 828.0], [595.0, 828.0]]], "lines": ["ＰｐｐＰＰＰ．．．"]}, {"box": [244, 1016, 264, 1121], "vertical": true, "font_size": 20, "lines_coords": [[[244.0, 1016.0], [264.0, 1016.0], [264.0, 1120.0], [244.0, 1120.0]]], "lines": ["さよなら．．．"]}]}