{"version": "0.1.7", "img_width": 847, "img_height": 1200, "blocks": [{"box": [714, 59, 741, 163], "vertical": true, "font_size": 20, "lines_coords": [[[715.0, 59.0], [735.0, 59.0], [735.0, 160.0], [715.0, 160.0]]], "lines": ["その日の朝。"]}, {"box": [446, 42, 476, 126], "vertical": true, "font_size": 21, "lines_coords": [[[446.0, 42.0], [467.0, 42.0], [469.0, 126.0], [448.0, 126.0]]], "lines": ["登校中に、"]}, {"box": [78, 57, 133, 213], "vertical": true, "font_size": 23, "lines_coords": [[[101.0, 57.0], [127.0, 57.0], [130.0, 159.0], [104.0, 159.0]], [[78.0, 59.0], [98.0, 59.0], [98.0, 213.0], [78.0, 213.0]]], "lines": ["謎の地図を", "拾ってしまった．．．"]}, {"box": [701, 410, 756, 526], "vertical": true, "font_size": 20, "lines_coords": [[[727.0, 410.0], [748.0, 410.0], [746.0, 526.0], [725.0, 526.0]], [[701.0, 411.0], [721.0, 411.0], [721.0, 488.0], [701.0, 488.0]]], "lines": ["帰りに探しに", "行くか！！"]}, {"box": [454, 411, 504, 553], "vertical": true, "font_size": 24, "lines_coords": [[[475.0, 411.0], [504.0, 411.0], [504.0, 481.0], [475.0, 481.0]], [[454.0, 413.0], [474.0, 413.0], [474.0, 551.0], [454.0, 551.0]]], "lines": ["ふふふ、", "何があるのやら。"]}, {"box": [381, 414, 408, 540], "vertical": true, "font_size": 21, "lines_coords": [[[381.0, 414.0], [402.0, 414.0], [404.0, 539.0], [383.0, 539.0]]], "lines": ["楽しみだなぁ。"]}, {"box": [58, 416, 112, 479], "vertical": true, "font_size": 30, "lines_coords": [[[87.0, 419.0], [110.0, 418.0], [112.0, 478.0], [90.0, 479.0]], [[58.0, 416.0], [96.0, 416.0], [96.0, 472.0], [58.0, 472.0]]], "lines": ["おはよ", "西片。"]}, {"box": [576, 1050, 610, 1123], "vertical": true, "font_size": 34, "lines_coords": [[[576.0, 1050.0], [610.0, 1050.0], [610.0, 1123.0], [576.0, 1123.0]]], "lines": ["ささっ"]}, {"box": [111, 910, 138, 1046], "vertical": true, "font_size": 23, "lines_coords": [[[111.0, 910.0], [134.0, 910.0], [134.0, 1046.0], [111.0, 1046.0]]], "lines": ["何持ってんの？"]}]}