{"version": "0.1.6", "img_width": 1350, "img_height": 1920, "blocks": [{"box": [1102, 174, 1201, 570], "vertical": true, "font_size": 30, "lines_coords": [[[1170.0, 176.0], [1201.0, 176.0], [1201.0, 429.0], [1170.0, 429.0]], [[1134.0, 174.0], [1166.0, 174.0], [1168.0, 570.0], [1136.0, 570.0]], [[1102.0, 176.0], [1128.0, 176.0], [1128.0, 511.0], [1102.0, 511.0]]], "lines": ["それに先輩が夏休み", "ママチャリで毎日５０キロ走って", "ダイエットした話を聞いて"]}, {"box": [300, 232, 399, 540], "vertical": true, "font_size": 28, "lines_coords": [[[365.0, 232.0], [397.0, 232.0], [397.0, 515.0], [365.0, 515.0]], [[331.0, 236.0], [358.0, 236.0], [358.0, 540.0], [331.0, 540.0]], [[300.0, 236.0], [326.0, 236.0], [326.0, 375.0], [300.0, 375.0]]], "lines": ["私はロードバイクだし", "案外行けるんじゃないか", "って思って"]}, {"box": [174, 416, 210, 510], "vertical": true, "font_size": 36, "lines_coords": [[[174.0, 418.0], [210.0, 418.0], [210.0, 510.0], [174.0, 510.0]]], "lines": ["ふーん"]}, {"box": [1100, 690, 1163, 930], "vertical": true, "font_size": 29, "lines_coords": [[[1136.0, 691.0], [1162.0, 691.0], [1162.0, 875.0], [1136.0, 875.0]], [[1100.0, 690.0], [1132.0, 690.0], [1132.0, 930.0], [1100.0, 930.0]]], "lines": ["そういえば絵真", "バイトの方はどう？"]}, {"box": [661, 701, 703, 802], "vertical": true, "font_size": 42, "lines_coords": [[[661.0, 701.0], [703.0, 701.0], [703.0, 802.0], [661.0, 802.0]]], "lines": ["うーん"]}, {"box": [183, 676, 278, 943], "vertical": true, "font_size": 28, "lines_coords": [[[249.0, 680.0], [275.0, 680.0], [275.0, 943.0], [249.0, 943.0]], [[213.0, 678.0], [245.0, 678.0], [245.0, 918.0], [213.0, 918.0]], [[185.0, 676.0], [211.0, 676.0], [210.0, 840.0], [183.0, 840.0]]], "lines": ["始めたばっかりだから", "覚えることが多くて", "ちょっと大変"]}, {"box": [1098, 1049, 1195, 1387], "vertical": true, "font_size": 26, "lines_coords": [[[1166.0, 1050.0], [1192.0, 1050.0], [1192.0, 1299.0], [1166.0, 1299.0]], [[1130.0, 1050.0], [1156.0, 1050.0], [1156.0, 1273.0], [1130.0, 1273.0]], [[1098.0, 1051.0], [1125.0, 1051.0], [1125.0, 1387.0], [1098.0, 1387.0]]], "lines": ["今までアウトドアに", "興味無かったから", "商品知識とかまるで無いし"]}, {"box": [585, 1003, 684, 1421], "vertical": true, "font_size": 26, "lines_coords": [[[656.0, 1005.0], [682.0, 1005.0], [682.0, 1421.0], [656.0, 1421.0]], [[620.0, 1005.0], [646.0, 1005.0], [646.0, 1310.0], [620.0, 1310.0]], [[586.0, 1003.0], [613.0, 1003.0], [611.0, 1254.0], [585.0, 1254.0]]], "lines": ["でも逆にアウトドア好きだったら", "あれもこれも欲しいって", "なっちゃいそうだね"]}, {"box": [178, 1042, 212, 1252], "vertical": true, "font_size": 26, "lines_coords": [[[180.0, 1044.0], [206.0, 1044.0], [206.0, 1252.0], [180.0, 1252.0]]], "lines": ["あーそれそれ"]}, {"box": [783, 1560, 817, 1659], "vertical": true, "font_size": 34, "lines_coords": [[[783.0, 1560.0], [817.0, 1560.0], [817.0, 1659.0], [783.0, 1659.0]]], "lines": ["あぁー"]}]}