{"version": "0.1.6", "img_width": 847, "img_height": 1200, "blocks": [{"box": [716, 558, 739, 676], "vertical": true, "font_size": 20.0, "lines": ["これなら．．．！！"]}, {"box": [415, 576, 470, 691], "vertical": true, "font_size": 20.0, "lines": ["間接キスでは", "ない！！"]}, {"box": [579, 936, 655, 1024], "vertical": true, "font_size": 16.0, "lines": ["ゲホゲホ！"]}, {"box": [183, 924, 268, 1025], "vertical": true, "font_size": 26.0, "lines": ["変な", "飲み方する", "からー。"]}, {"box": [141, 900, 168, 976], "vertical": true, "font_size": 25.0, "lines": ["あはは"]}]}