{"version": "0.1.6", "img_width": 722, "img_height": 1024, "blocks": [{"box": [495, 76, 538, 198], "vertical": true, "font_size": 20, "lines_coords": [[[516.0, 76.0], [538.0, 76.0], [538.0, 126.0], [516.0, 126.0]], [[496.0, 78.0], [513.0, 78.0], [512.0, 195.0], [495.0, 195.0]]], "lines": ["ここは", "心を鬼にして．．．"]}, {"box": [442, 148, 466, 182], "vertical": true, "font_size": 24, "lines_coords": [[[442.0, 148.0], [466.0, 148.0], [466.0, 182.0], [442.0, 182.0]]], "lines": ["あっ"]}, {"box": [305, 110, 322, 165], "vertical": true, "font_size": 17, "lines_coords": [[[305.0, 110.0], [322.0, 110.0], [322.0, 165.0], [305.0, 165.0]]], "lines": ["おいしー"]}, {"box": [316, 233, 340, 252], "vertical": false, "font_size": 19, "lines_coords": [[[316.0, 233.0], [340.0, 233.0], [340.0, 252.0], [316.0, 252.0]]], "lines": ["やぶっ"]}, {"box": [187, 118, 237, 190], "vertical": true, "font_size": 15, "lines_coords": [[[219.0, 118.0], [237.0, 118.0], [237.0, 170.0], [219.0, 170.0]], [[202.0, 119.0], [219.0, 119.0], [219.0, 186.0], [202.0, 186.0]], [[188.0, 121.0], [199.0, 121.0], [199.0, 190.0], [188.0, 190.0]]], "lines": ["なんだ．．．", "結局買って", "やったのか．．．"]}, {"box": [71, 88, 122, 164], "vertical": true, "font_size": 13, "lines_coords": [[[109.0, 90.0], [120.0, 90.0], [120.0, 164.0], [109.0, 164.0]], [[90.0, 89.0], [104.0, 89.0], [104.0, 151.0], [90.0, 151.0]], [[71.0, 88.0], [85.0, 88.0], [85.0, 140.0], [71.0, 140.0]]], "lines": ["すいません．．．", "負けちゃい", "ました．．"]}, {"box": [629, 311, 644, 406], "vertical": true, "font_size": 14, "lines_coords": [[[629.0, 311.0], [643.0, 311.0], [643.0, 405.0], [629.0, 405.0]]], "lines": ["でもやっぱり．．．"]}, {"box": [401, 334, 487, 399], "vertical": true, "font_size": 20, "lines_coords": [[[466.0, 335.0], [487.0, 335.0], [487.0, 399.0], [466.0, 399.0]], [[443.0, 334.0], [465.0, 334.0], [465.0, 399.0], [443.0, 399.0]], [[421.0, 334.0], [442.0, 334.0], [442.0, 399.0], [421.0, 399.0]], [[401.0, 335.0], [419.0, 335.0], [419.0, 398.0], [401.0, 398.0]]], "lines": ["かって！！", "かって！！", "かって！！", "かって！！"]}, {"box": [285, 307, 320, 428], "vertical": true, "font_size": 14, "lines_coords": [[[305.0, 307.0], [319.0, 307.0], [319.0, 375.0], [305.0, 375.0]], [[285.0, 309.0], [299.0, 309.0], [299.0, 427.0], [285.0, 427.0]]], "lines": ["このガキは", "なんだかんだいって"]}, {"box": [206, 324, 218, 367], "vertical": true, "font_size": 12, "lines_coords": [[[206.0, 324.0], [218.0, 324.0], [218.0, 367.0], [206.0, 367.0]]], "lines": ["あー"]}, {"box": [77, 310, 116, 420], "vertical": true, "font_size": 16, "lines_coords": [[[94.0, 310.0], [111.0, 310.0], [114.0, 406.0], [97.0, 406.0]], [[77.0, 311.0], [92.0, 311.0], [93.0, 419.0], [78.0, 419.0]]], "lines": ["癇癪起こしての", "ワガママ放題だな"]}, {"box": [626, 534, 640, 614], "vertical": true, "font_size": 14, "lines_coords": [[[626.0, 534.0], [640.0, 534.0], [640.0, 614.0], [626.0, 614.0]]], "lines": ["でもここは："]}, {"box": [502, 588, 518, 612], "vertical": true, "font_size": 16, "lines_coords": [[[502.0, 590.0], [518.0, 590.0], [518.0, 612.0], [502.0, 612.0]]], "lines": ["あっ"]}, {"box": [288, 531, 333, 622], "vertical": true, "font_size": 18, "lines_coords": [[[310.0, 531.0], [328.0, 531.0], [329.0, 622.0], [311.0, 622.0]], [[288.0, 531.0], [307.0, 531.0], [307.0, 580.0], [288.0, 580.0]]], "lines": ["少し注意して", "やるか"]}, {"box": [210, 543, 255, 582], "vertical": true, "font_size": 26, "lines_coords": [[[230.0, 544.0], [255.0, 544.0], [255.0, 580.0], [230.0, 580.0]], [[210.0, 543.0], [238.0, 543.0], [238.0, 582.0], [210.0, 582.0]]], "lines": ["おい", "ガキ"]}, {"box": [88, 565, 148, 686], "vertical": true, "font_size": 16, "lines_coords": [[[129.0, 566.0], [146.0, 566.0], [146.0, 641.0], [129.0, 641.0]], [[108.0, 565.0], [125.0, 565.0], [124.0, 685.0], [107.0, 685.0]], [[88.0, 565.0], [102.0, 565.0], [102.0, 640.0], [88.0, 640.0]]], "lines": ["いいわけん", "ガマンという事を", "覚えろよ！"]}, {"box": [626, 766, 642, 833], "vertical": true, "font_size": 14, "lines_coords": [[[627.0, 767.0], [641.0, 767.0], [641.0, 832.0], [627.0, 832.0]]], "lines": ["やっぱり．．．"]}, {"box": [415, 768, 455, 859], "vertical": true, "font_size": 18, "lines_coords": [[[437.0, 769.0], [455.0, 769.0], [455.0, 859.0], [437.0, 859.0]], [[415.0, 769.0], [432.0, 769.0], [432.0, 859.0], [415.0, 859.0]]], "lines": ["かってがって", "がってかって"]}, {"box": [298, 769, 316, 851], "vertical": true, "font_size": 17, "lines_coords": [[[299.0, 769.0], [316.0, 769.0], [316.0, 851.0], [299.0, 851.0]]], "lines": ["わかった！！"]}, {"box": [195, 767, 232, 803], "vertical": false, "font_size": 36, "lines_coords": [[[195.0, 767.0], [232.0, 767.0], [232.0, 803.0], [195.0, 803.0]]], "lines": ["いや！！"]}, {"box": [137, 829, 179, 892], "vertical": true, "font_size": 18, "lines_coords": [[[161.0, 831.0], [179.0, 831.0], [179.0, 891.0], [161.0, 891.0]], [[139.0, 829.0], [157.0, 829.0], [155.0, 892.0], [137.0, 892.0]]], "lines": ["わかって", "ねーよ！！！"]}, {"box": [67, 757, 116, 907], "vertical": true, "font_size": 19, "lines_coords": [[[90.0, 757.0], [111.0, 757.0], [111.0, 827.0], [90.0, 827.0]], [[68.0, 757.0], [85.0, 757.0], [85.0, 907.0], [68.0, 907.0]]], "lines": ["東雲家は", "今日も平和であった"]}, {"box": [74, 966, 229, 985], "vertical": false, "font_size": 18, "lines_coords": [[[74.0, 966.0], [229.0, 967.0], [229.0, 985.0], [74.0, 984.0]]], "lines": ["１常の９３（おわり"]}]}