{"version": "0.2.0-beta.6", "img_width": 1100, "img_height": 1600, "blocks": [{"box": [889, 514, 925, 623], "vertical": true, "font_size": 32, "lines_coords": [[[889.0, 514.0], [921.0, 514.0], [925.0, 623.0], [892.0, 623.0]]], "lines": ["奴が．．．"]}, {"box": [214, 735, 256, 903], "vertical": true, "font_size": 39, "lines_coords": [[[214.0, 735.0], [253.0, 735.0], [253.0, 903.0], [214.0, 903.0]]], "lines": ["．．．来る！！"]}, {"box": [37, 1021, 75, 1437], "vertical": true, "font_size": 38, "lines_coords": [[[37.0, 1021.0], [75.0, 1021.0], [75.0, 1437.0], [37.0, 1437.0]]], "lines": ["「おやすみプンプンの一完、"]}]}