{"version": "0.1.6", "img_width": 847, "img_height": 1200, "blocks": [{"box": [652, 103, 732, 257], "vertical": true, "font_size": 23.0, "lines": ["大凶から大吉まで", "一枚ずつ計７枚", "袋に入ってる。"]}, {"box": [167, 75, 277, 194], "vertical": true, "font_size": 25.0, "lines": ["交互に引いて", "先に大吉を", "引いた方の", "勝ち。"]}, {"box": [64, 103, 91, 173], "vertical": true, "font_size": 25.0, "lines": ["ふーん。"]}, {"box": [697, 495, 751, 621], "vertical": true, "font_size": 20.0, "lines": ["じゃ、高木さん", "先攻どうぞ。"]}, {"box": [410, 502, 461, 590], "vertical": true, "font_size": 24.0, "lines": ["へえ", "余裕だね。"]}, {"box": [299, 492, 354, 619], "vertical": true, "font_size": 22.0, "lines": ["まぁ、運勢一位", "だからね。"]}, {"box": [658, 833, 753, 923], "vertical": true, "font_size": 22.0, "lines": ["あ", "その前に．．", "ちょっと", "待って。"]}, {"box": [206, 832, 230, 882], "vertical": true, "font_size": 22.0, "lines": ["よし。"]}]}