{"version": "0.1.7", "img_width": 10550, "img_height": 1200, "blocks": [{"box": [4132, 110, 4932, 560], "vertical": false, "font_size": 495, "lines_coords": [[[4132.0, 65.0], [4932.0, 65.0], [4932.0, 605.0], [4132.0, 605.0]]], "lines": ["いー、ホームページについては、"]}, {"box": [2060, 62, 4904, 1138], "vertical": false, "font_size": 158, "lines_coords": [[[4388.0, 120.0], [4543.0, 120.0], [4543.0, 231.0], [4388.0, 231.0]], [[4100.0, 254.0], [4811.0, 99.0], [4842.0, 272.0], [4131.0, 427.0]], [[4069.0, 368.0], [4883.0, 213.0], [4904.0, 365.0], [4090.0, 510.0]], [[2163.0, 430.0], [3987.0, 399.0], [3987.0, 593.0], [2163.0, 624.0]], [[4275.0, 441.0], [4780.0, 348.0], [4801.0, 520.0], [4296.0, 603.0]], [[2060.0, 565.0], [4172.0, 565.0], [4172.0, 810.0], [2060.0, 810.0]], [[2081.0, 782.0], [4770.0, 803.0], [4770.0, 965.0], [2081.0, 945.0]], [[2081.0, 948.0], [3595.0, 948.0], [3595.0, 1120.0], [2081.0, 1120.0]]], "lines": ["．．．", "２０１０万部突破感謝！！キペーカーもバスクオリ", "意バーカーはパスタオル", "コールス名越の選ばかついに明らかに！！", "一方一番バスクス大プレゼント！！", "選択とクラミックスビルグス人気選挙のお", "«作品中のトレバネーションは極めて危険な行為です。", "«〈中間〉《絶対に真似をしないでください。"]}, {"box": [134, 888, 1478, 1080], "vertical": false, "font_size": 79, "lines_coords": [[[247.0, 903.0], [1339.0, 903.0], [1339.0, 989.0], [247.0, 989.0]], [[154.0, 986.0], [1421.0, 986.0], [1421.0, 1072.0], [154.0, 1072.0]]], "lines": ["ビッグコミックスのデー一夕満載のホームページ。", "ｈｔｔｐ：，ｗｗｗ．ｂｉｇｏｎ：ｍａｓ．ｓｈｏｇａｋｕｋａｎ．ｃｏ．"]}, {"box": [6150, 74, 7933, 1130], "vertical": false, "font_size": 141, "lines_coords": [[[6150.0, 81.0], [7881.0, 70.0], [7881.0, 208.0], [6150.0, 218.0]], [[6490.0, 225.0], [7737.0, 225.0], [7737.0, 384.0], [6490.0, 384.0]], [[6243.0, 360.0], [7830.0, 370.0], [7830.0, 601.0], [6243.0, 591.0]], [[7129.0, 660.0], [7675.0, 660.0], [7675.0, 787.0], [7129.0, 787.0]], [[6439.0, 774.0], [6913.0, 774.0], [6913.0, 912.0], [6439.0, 912.0]], [[7253.0, 784.0], [7778.0, 784.0], [7778.0, 912.0], [7253.0, 912.0]]], "lines": ["緊急コミの情報を使用していますが、まだまだチケットに", "パーティー名バスクオレを", "許３００名様に大プレゼント！！", "各プランドＢｏｎｇ製！！（日）", "１００名様", "２００名様"]}, {"box": [8747, 113, 10253, 1102], "vertical": false, "font_size": 119, "lines_coords": [[[8777.0, 134.0], [10220.0, 134.0], [10220.0, 258.0], [8777.0, 258.0]], [[8788.0, 269.0], [10210.0, 258.0], [10210.0, 361.0], [8788.0, 372.0]], [[8788.0, 352.0], [10199.0, 341.0], [10199.0, 434.0], [8788.0, 444.0]], [[8777.0, 403.0], [10220.0, 372.0], [10220.0, 496.0], [8777.0, 527.0]], [[8808.0, 496.0], [10024.0, 496.0], [10024.0, 558.0], [8808.0, 558.0]], [[8747.0, 517.0], [10251.0, 496.0], [10251.0, 734.0], [8747.0, 754.0]], [[8747.0, 652.0], [9787.0, 652.0], [9787.0, 889.0], [8747.0, 889.0]], [[8788.0, 838.0], [9859.0, 838.0], [9859.0, 930.0], [8788.0, 930.0]], [[8819.0, 900.0], [9777.0, 900.0], [9777.0, 992.0], [8819.0, 992.0]]], "lines": ["ユールームレスタイルオフィンセンタイプランチ", "●応募方法、官製ハガキに右下の住所３氏名４年齢５層話番この応募券を貼って、（郵便番号）号も職業（学年）このご希望の普品", "●応募方法：冒製バカキに右１２年齢５電話番号４またはＢとサイズレーカーのこの応募券を貼って、「郵便番号号０職業（学年）７こ希望の賞品」のみ、メンズのＳＩＭＬの", "２０１５年１月２６日に第３期番号に参加しておりますが、それまでは仕事とサイズバーカーのメンズのようです。大丈夫だったのですよね！！", "そんなことは、ズです。を明記の上、「本で生・三１０」の下記のあて先にお送りください。東言数千代田区ーツ様のことが", "ちょっとしているのですが、大きすぎだったんだけど、あんまり大きくありました。あのまま、今まで一緒になったことでしょうかもしれません。ブロックスコミックロードですからないですよ。", "クエックスピリック撮影はオンクレスト・ルフレイピント１４年１２０１７年１月１１日日日金沢田会津田市南海港区東京区の発表に東京に発送されていました。", "このタダルバムの中からは、自分の小学生は英語の発送をもっていませていただきます。", "「発表時時点の発送をして代させていただきましたが、ご記入いたい」と思います。ご協力・ご連絡はお嬢様品のお届けの目的以外には失敗しませんです。"]}]}