{"version": "0.1.7", "img_width": 832, "img_height": 1200, "blocks": [{"box": [111, 120, 394, 202], "vertical": false, "font_size": 26, "lines_coords": [[[114.0, 124.0], [389.0, 121.0], [389.0, 153.0], [114.0, 155.0]], [[166.0, 176.0], [329.0, 176.0], [329.0, 196.0], [166.0, 196.0]]], "lines": ["ホムンクルス６", "ビッグコミックス"]}, {"box": [155, 563, 226, 591], "vertical": false, "font_size": 22, "lines_coords": [[[155.0, 566.0], [224.0, 563.0], [226.0, 589.0], [157.0, 591.0]]], "lines": ["者著"]}, {"box": [171, 455, 467, 472], "vertical": false, "font_size": 17, "lines_coords": [[[171.0, 455.0], [467.0, 455.0], [467.0, 472.0], [171.0, 472.0]]], "lines": ["２００５年１０月１日初版第１刷発行"]}, {"box": [468, 414, 738, 431], "vertical": false, "font_size": 17, "lines_coords": [[[468.0, 414.0], [738.0, 414.0], [738.0, 431.0], [468.0, 431.0]]], "lines": ["ＩＳＢＮ４－０９－１８７０７６－７"]}, {"box": [652, 452, 739, 475], "vertical": false, "font_size": 19, "lines_coords": [[[656.0, 453.0], [734.0, 453.0], [734.0, 474.0], [656.0, 474.0]]], "lines": ["（検印廃止）"]}, {"box": [158, 643, 226, 703], "vertical": false, "font_size": 22, "lines_coords": [[[158.0, 643.0], [226.0, 643.0], [226.0, 667.0], [158.0, 667.0]], [[161.0, 683.0], [223.0, 685.0], [223.0, 703.0], [161.0, 700.0]]], "lines": ["発行者", "だけどいって"]}, {"box": [114, 808, 210, 842], "vertical": false, "font_size": 34, "lines_coords": [[[114.0, 808.0], [210.0, 808.0], [210.0, 842.0], [114.0, 842.0]]], "lines": ["発行所"]}, {"box": [112, 745, 317, 786], "vertical": false, "font_size": 20, "lines_coords": [[[116.0, 746.0], [310.0, 746.0], [310.0, 762.0], [116.0, 762.0]], [[112.0, 762.0], [266.0, 762.0], [266.0, 786.0], [112.0, 786.0]]], "lines": ["単行本編集責任ノ赤名英之", "単行本編集／銀杏社"]}, {"box": [356, 564, 622, 704], "vertical": false, "font_size": 21, "lines_coords": [[[358.0, 565.0], [532.0, 562.0], [532.0, 591.0], [358.0, 593.0]], [[363.0, 607.0], [616.0, 607.0], [616.0, 627.0], [363.0, 627.0]], [[356.0, 642.0], [428.0, 642.0], [428.0, 666.0], [356.0, 666.0]], [[509.0, 646.0], [529.0, 646.0], [529.0, 666.0], [509.0, 666.0]], [[359.0, 683.0], [527.0, 684.0], [527.0, 705.0], [359.0, 703.0]]], "lines": ["大丈夫です。", "○Ｈｉｔｅｏ．Ｙａｍａｎｏｔｏ！！！", "原笹", "博", "凸版印刷株式会社"]}, {"box": [240, 847, 444, 862], "vertical": false, "font_size": 15, "lines_coords": [[[240.0, 847.0], [444.0, 847.0], [444.0, 862.0], [240.0, 862.0]]], "lines": ["振替（００１８０＿１－－２００）ＴＥＬ"]}, {"box": [242, 802, 577, 819], "vertical": false, "font_size": 16, "lines_coords": [[[242.0, 803.0], [577.0, 802.0], [577.0, 817.0], [242.0, 819.0]]], "lines": ["〈〒１０１－８００Ｄ東京都千代田区一ツ橋二の三の"]}, {"box": [453, 835, 588, 871], "vertical": false, "font_size": 15.5, "lines_coords": [[[453.0, 836.0], [587.0, 835.0], [587.0, 851.0], [453.0, 853.0]], [[454.0, 856.0], [588.0, 856.0], [588.0, 871.0], [454.0, 871.0]]], "lines": ["編集１０３（３２３０）５５０５", "収売０８（５２８１）３５６"]}, {"box": [622, 702, 747, 725], "vertical": false, "font_size": 15, "lines_coords": [[[629.0, 704.0], [739.0, 705.0], [739.0, 722.0], [629.0, 721.0]]], "lines": ["ＰｒｉｎｔｅｄｉｎＪａｐａｎ"]}, {"box": [629, 849, 744, 892], "vertical": false, "font_size": 23.5, "lines_coords": [[[635.0, 851.0], [678.0, 851.0], [678.0, 869.0], [635.0, 869.0]], [[629.0, 863.0], [740.0, 849.0], [744.0, 878.0], [632.0, 892.0]]], "lines": ["株式", "会社小学館"]}, {"box": [134, 1038, 254, 1053], "vertical": false, "font_size": 15, "lines_coords": [[[134.0, 1038.0], [254.0, 1038.0], [254.0, 1053.0], [134.0, 1053.0]]], "lines": ["アンケートのお願い"]}, {"box": [116, 903, 699, 1031], "vertical": false, "font_size": 14, "lines_coords": [[[116.0, 902.0], [699.0, 903.0], [699.0, 923.0], [116.0, 921.0]], [[117.0, 920.0], [616.0, 920.0], [616.0, 935.0], [117.0, 935.0]], [[117.0, 935.0], [274.0, 935.0], [274.0, 951.0], [117.0, 951.0]], [[118.0, 950.0], [619.0, 950.0], [619.0, 966.0], [118.0, 966.0]], [[119.0, 967.0], [550.0, 967.0], [550.0, 979.0], [119.0, 979.0]], [[118.0, 980.0], [326.0, 980.0], [326.0, 995.0], [118.0, 995.0]], [[118.0, 995.0], [615.0, 995.0], [615.0, 1010.0], [118.0, 1010.0]], [[118.0, 1010.0], [558.0, 1010.0], [558.0, 1026.0], [118.0, 1026.0]]], "lines": ["●店本には十分注意しておりますが、また「キャッシュアル」を「飛行工事件のページの投げ落ち着けの間違いが悪い」ということはありません。ですが、いつの場合はお取り替えいたします。加藤さんにまず", "購入された書店名を明記してまったくは一般的に居てにお送りください。選択はっ、戦いつの間違いですから、小社員用にてお取り替えていたします。", "新作品（ＴＥＢＩＴＥＬＩＮＥＴ）ＬＩＤＩＳＩＳＥＯＫＡＮＡＴＡＮＴ", "あれは、ユーザーのみなので、●本書の一部あるいは全部を無視しません。それじゃないですね。で複製素戦・上演・放送学をすることはいえません。とは、法律で認められた場合を除き、", "著作者および出版者の権利の役割となります。あらかじめ小社あで詐諾をお求めください。", "国（日本複写権センタ委託出版物", "本書の一部まではコンタクトの本語の「部または全部を無断で終了しました。スタッフビーすることは、著作権法上での例外を除き禁じられています。", "本当の部屋には上側と複写を希望される場合は、日本被写権センター（ＴＥＢ）のＷｉｎｄｏｗｓということで、３００１．２８８３８以上ご連絡ください。"]}, {"box": [308, 1037, 413, 1052], "vertical": false, "font_size": 10, "lines_coords": [[[312.0, 1038.0], [405.0, 1038.0], [405.0, 1050.0], [312.0, 1050.0]]], "lines": ["小学館アンケート係"]}, {"box": [126, 1066, 620, 1144], "vertical": false, "font_size": 14, "lines_coords": [[[137.0, 1066.0], [573.0, 1066.0], [573.0, 1082.0], [137.0, 1082.0]], [[134.0, 1081.0], [449.0, 1081.0], [449.0, 1097.0], [134.0, 1097.0]], [[137.0, 1097.0], [431.0, 1097.0], [431.0, 1112.0], [137.0, 1112.0]], [[137.0, 1112.0], [616.0, 1112.0], [616.0, 1128.0], [137.0, 1128.0]], [[137.0, 1127.0], [563.0, 1127.0], [563.0, 1143.0], [137.0, 1143.0]]], "lines": ["●小学館のコミックス、書籍についてのアンケートをイシターネットで受け付けています。", "トレーナル．．．わざわざワードやＷｉｎｄｏｗｓｔｏｒｄｏｒｋｉｃｋｏｒ２０１７にアクセスしていただき、", "このコミックスのキーコーお兄ちゃんのお母さんの名前を入力してください。", "●全ご回答者の中から、毎年１５００万円ですので、利用者の方に利益で、小学的な情報を書かれますが、「ドイロの切りをさしあげます。", "●発行日より６か月間有効です。●発表は貴品の発送をもああはははってかえさせていただきます。"]}]}