{"version": "0.1.7", "img_width": 840, "img_height": 1200, "blocks": [{"box": [619, 22, 646, 73], "vertical": true, "font_size": 27, "lines_coords": [[[619.0, 22.0], [646.0, 22.0], [646.0, 73.0], [619.0, 73.0]]], "lines": ["え？"]}, {"box": [611, 117, 636, 198], "vertical": true, "font_size": 25, "lines_coords": [[[611.0, 117.0], [636.0, 117.0], [636.0, 198.0], [611.0, 198.0]]], "lines": ["お金．．．．．"]}, {"box": [495, 21, 520, 101], "vertical": true, "font_size": 25, "lines_coords": [[[495.0, 21.0], [520.0, 21.0], [520.0, 101.0], [495.0, 101.0]]], "lines": ["いや．．．"]}, {"box": [342, 17, 390, 118], "vertical": true, "font_size": 24, "lines_coords": [[[364.0, 17.0], [390.0, 17.0], [390.0, 80.0], [364.0, 80.0]], [[344.0, 17.0], [365.0, 17.0], [363.0, 118.0], [342.0, 118.0]]], "lines": ["ただの", "紙ですか？"]}, {"box": [221, 21, 267, 125], "vertical": true, "font_size": 20, "lines_coords": [[[247.0, 21.0], [267.0, 21.0], [267.0, 117.0], [247.0, 117.0]], [[221.0, 21.0], [242.0, 21.0], [243.0, 125.0], [222.0, 125.0]]], "lines": ["フェリスの", "お嬢様には、"]}, {"box": [101, 21, 144, 117], "vertical": true, "font_size": 20, "lines_coords": [[[124.0, 21.0], [144.0, 21.0], [144.0, 117.0], [124.0, 117.0]], [[101.0, 22.0], [118.0, 22.0], [118.0, 117.0], [101.0, 117.0]]], "lines": ["わからない", "かなあ．．．．．"]}, {"box": [494, 482, 589, 621], "vertical": true, "font_size": 23, "lines_coords": [[[564.0, 483.0], [589.0, 483.0], [589.0, 582.0], [564.0, 582.0]], [[543.0, 483.0], [563.0, 483.0], [563.0, 601.0], [543.0, 601.0]], [[516.0, 482.0], [540.0, 482.0], [540.0, 621.0], [516.0, 621.0]], [[494.0, 482.0], [516.0, 482.0], [516.0, 525.0], [494.0, 525.0]]], "lines": ["いやらしい", "プレッシャー", "かけるんですね", "．．．．．"]}, {"box": [339, 465, 359, 553], "vertical": true, "font_size": 20, "lines_coords": [[[339.0, 465.0], [359.0, 465.0], [359.0, 553.0], [339.0, 553.0]]], "lines": ["よく見て。"]}, {"box": [777, 793, 798, 897], "vertical": true, "font_size": 20, "lines_coords": [[[777.0, 793.0], [797.0, 793.0], [797.0, 897.0], [777.0, 897.0]]], "lines": ["千円という、"]}, {"box": [639, 802, 665, 864], "vertical": true, "font_size": 26, "lines_coords": [[[639.0, 802.0], [665.0, 802.0], [665.0, 864.0], [639.0, 864.0]]], "lines": ["価値？"]}, {"box": [104, 639, 160, 699], "vertical": true, "font_size": 32, "lines_coords": [[[121.0, 643.0], [154.0, 639.0], [160.0, 696.0], [127.0, 699.0]], [[104.0, 642.0], [135.0, 642.0], [135.0, 690.0], [104.0, 690.0]]], "lines": ["これ、", "何？"]}, {"box": [477, 1042, 541, 1153], "vertical": true, "font_size": 27, "lines_coords": [[[515.0, 1045.0], [540.0, 1045.0], [540.0, 1153.0], [515.0, 1153.0]], [[477.0, 1042.0], [507.0, 1042.0], [509.0, 1141.0], [480.0, 1141.0]]], "lines": ["借用証書", "でしょ。"]}]}