{"version": "0.1.6", "img_width": 1350, "img_height": 1920, "blocks": [{"box": [1136, 140, 1211, 421], "vertical": true, "font_size": 36, "lines_coords": [[[1179.0, 142.0], [1211.0, 142.0], [1211.0, 421.0], [1179.0, 421.0]], [[1136.0, 144.0], [1175.0, 144.0], [1175.0, 270.0], [1136.0, 270.0]]], "lines": ["なぁなぁお嬢ちゃん", "一人旅？"]}, {"box": [885, 151, 971, 376], "vertical": true, "font_size": 39, "lines_coords": [[[933.0, 157.0], [971.0, 157.0], [971.0, 376.0], [933.0, 376.0]], [[888.0, 151.0], [928.0, 151.0], [924.0, 339.0], [885.0, 339.0]]], "lines": ["一緒にお菓子", "食べへん？"]}, {"box": [140, 255, 214, 420], "vertical": true, "font_size": 30, "lines_coords": [[[180.0, 256.0], [211.0, 256.0], [211.0, 420.0], [180.0, 420.0]], [[144.0, 255.0], [172.0, 255.0], [168.0, 384.0], [140.0, 384.0]]], "lines": ["じゃ私のも", "どうぞー"]}, {"box": [401, 551, 489, 740], "vertical": true, "font_size": 40, "lines_coords": [[[442.0, 551.0], [489.0, 551.0], [489.0, 671.0], [442.0, 671.0]], [[403.0, 553.0], [435.0, 553.0], [435.0, 740.0], [403.0, 740.0]]], "lines": ["いいん", "ですかっ？"]}, {"box": [789, 843, 860, 1186], "vertical": true, "font_size": 33, "lines_coords": [[[826.0, 849.0], [860.0, 849.0], [858.0, 1125.0], [825.0, 1125.0]], [[789.0, 847.0], [821.0, 847.0], [821.0, 1186.0], [789.0, 1186.0]]], "lines": ["へぇーお姉さん達は", "三重から来たんですかぁ"]}, {"box": [415, 1089, 485, 1305], "vertical": true, "font_size": 26, "lines_coords": [[[453.0, 1089.0], [480.0, 1089.0], [480.0, 1245.0], [453.0, 1245.0]], [[416.0, 1091.0], [442.0, 1091.0], [442.0, 1305.0], [416.0, 1305.0]]], "lines": ["奥静の秘境", "を目指してなぁ"]}, {"box": [1162, 1342, 1220, 1666], "vertical": true, "font_size": 25, "lines_coords": [[[1194.0, 1344.0], [1220.0, 1344.0], [1220.0, 1541.0], [1194.0, 1541.0]], [[1162.0, 1342.0], [1186.0, 1342.0], [1186.0, 1666.0], [1162.0, 1666.0]]], "lines": ["ホンマは桜満開の", "４月頭に来たかったんやけど"]}, {"box": [1070, 1475, 1126, 1800], "vertical": true, "font_size": 25, "lines_coords": [[[1100.0, 1477.0], [1126.0, 1477.0], [1126.0, 1800.0], [1100.0, 1800.0]], [[1070.0, 1475.0], [1095.0, 1475.0], [1095.0, 1751.0], [1070.0, 1751.0]]], "lines": ["この人が人混みは嫌やーって", "言うから今週にしたんよ。"]}, {"box": [466, 1492, 537, 1743], "vertical": true, "font_size": 29, "lines_coords": [[[508.0, 1496.0], [534.0, 1496.0], [534.0, 1710.0], [508.0, 1710.0]], [[466.0, 1492.0], [498.0, 1492.0], [498.0, 1743.0], [466.0, 1743.0]]], "lines": ["混雑しとったら", "秘境感薄れるやん"]}]}