{"version": "0.1.6", "img_width": 1350, "img_height": 1920, "blocks": [{"box": [926, 1200, 1066, 1644], "vertical": true, "font_size": 63, "lines_coords": [[[997.0, 1207.0], [1053.0, 1205.0], [1066.0, 1548.0], [1010.0, 1550.0]], [[926.0, 1200.0], [995.0, 1200.0], [999.0, 1644.0], [930.0, 1644.0]]], "lines": ["このハンバーグ", "通販でも買えるわよ"]}, {"box": [63, 1252, 135, 1605], "vertical": true, "font_size": 72, "lines_coords": [[[63.0, 1267.0], [135.0, 1267.0], [135.0, 1605.0], [63.0, 1605.0]]], "lines": ["そうなの！？"]}]}