{"version": "0.1.6", "img_width": 722, "img_height": 1024, "blocks": [{"box": [398, 57, 570, 106], "vertical": false, "font_size": 49, "lines_coords": [[[398.0, 57.0], [570.0, 57.0], [570.0, 106.0], [398.0, 106.0]]], "lines": ["日常の５５"]}, {"box": [312, 115, 331, 216], "vertical": true, "font_size": 17, "lines_coords": [[[313.0, 116.0], [330.0, 116.0], [330.0, 216.0], [313.0, 216.0]]], "lines": ["もーいーかい"]}, {"box": [110, 138, 124, 216], "vertical": true, "font_size": 14, "lines_coords": [[[110.0, 139.0], [124.0, 139.0], [124.0, 215.0], [110.0, 215.0]]], "lines": ["もーいーよー"]}, {"box": [299, 324, 338, 436], "vertical": true, "font_size": 16, "lines_coords": [[[321.0, 324.0], [338.0, 324.0], [338.0, 436.0], [321.0, 436.0]], [[300.0, 325.0], [314.0, 325.0], [314.0, 428.0], [300.0, 428.0]]], "lines": ["よーしっじゃー", "さがしますよー"]}, {"box": [115, 332, 155, 438], "vertical": true, "font_size": 18, "lines_coords": [[[133.0, 332.0], [155.0, 332.0], [155.0, 382.0], [133.0, 382.0]], [[115.0, 333.0], [129.0, 333.0], [129.0, 438.0], [115.0, 438.0]]], "lines": ["はかせ", "どこですか～？"]}, {"box": [293, 560, 316, 633], "vertical": true, "font_size": 17, "lines_coords": [[[296.0, 605.0], [313.0, 605.0], [313.0, 630.0], [296.0, 630.0]]], "lines": ["え"]}, {"box": [218, 836, 273, 868], "vertical": false, "font_size": 11, "lines_coords": [[[218.0, 858.0], [269.0, 836.0], [273.0, 846.0], [222.0, 868.0]]], "lines": ["にギリエイ"]}]}