{"version": "0.1.6", "img_width": 722, "img_height": 1024, "blocks": [{"box": [557, 632, 587, 754], "vertical": true, "font_size": 20, "lines_coords": [[[559.0, 633.0], [579.0, 633.0], [579.0, 753.0], [559.0, 753.0]]], "lines": ["根拠はないが"]}, {"box": [191, 628, 280, 831], "vertical": true, "font_size": 20, "lines_coords": [[[250.0, 630.0], [271.0, 630.0], [271.0, 751.0], [250.0, 751.0]], [[220.0, 628.0], [241.0, 628.0], [240.0, 829.0], [219.0, 829.0]], [[193.0, 630.0], [210.0, 630.0], [210.0, 829.0], [193.0, 829.0]]], "lines": ["少し笹原との", "距離が縮まったような", "気がしたみおであった"]}, {"box": [482, 968, 653, 989], "vertical": false, "font_size": 21, "lines_coords": [[[482.0, 968.0], [653.0, 968.0], [653.0, 989.0], [482.0, 989.0]]], "lines": ["日常の４３（おわり）"]}, {"box": [137, 719, 171, 849], "vertical": true, "font_size": 17, "lines_coords": [[[154.0, 719.0], [171.0, 719.0], [171.0, 793.0], [154.0, 793.0]]], "lines": ["みおちゃん"]}]}