{"version": "0.1.7", "img_width": 843, "img_height": 1200, "blocks": [{"box": [669, 65, 721, 161], "vertical": true, "font_size": 25, "lines_coords": [[[696.0, 67.0], [721.0, 67.0], [721.0, 153.0], [696.0, 153.0]], [[669.0, 65.0], [694.0, 65.0], [694.0, 161.0], [669.0, 161.0]]], "lines": ["安心して", "ください。"]}, {"box": [325, 62, 433, 212], "vertical": true, "font_size": 21, "lines_coords": [[[410.0, 62.0], [433.0, 62.0], [433.0, 212.0], [410.0, 212.0]], [[383.0, 62.0], [404.0, 62.0], [404.0, 167.0], [383.0, 167.0]], [[358.0, 64.0], [375.0, 64.0], [375.0, 169.0], [358.0, 169.0]], [[325.0, 62.0], [349.0, 62.0], [352.0, 198.0], [329.0, 198.0]]], "lines": ["はっきり言って", "そこら辺の", "医者よりも", "腕は確かです。"]}, {"box": [36, 716, 84, 793], "vertical": true, "font_size": 42, "lines_coords": [[[36.0, 719.0], [78.0, 716.0], [84.0, 789.0], [42.0, 793.0]]], "lines": ["やれ。"]}]}