{"version": "0.1.7", "img_width": 843, "img_height": 1200, "blocks": [{"box": [65, 560, 446, 603], "vertical": false, "font_size": 43, "lines_coords": [[[65.0, 560.0], [446.0, 560.0], [446.0, 603.0], [65.0, 603.0]]], "lines": ["［ホムンクルス］第１集＂完"]}, {"box": [51, 1060, 631, 1127], "vertical": false, "font_size": 16, "lines_coords": [[[60.0, 1058.0], [623.0, 1059.0], [623.0, 1076.0], [60.0, 1075.0]], [[60.0, 1073.0], [596.0, 1074.0], [596.0, 1094.0], [60.0, 1093.0]], [[62.0, 1093.0], [437.0, 1093.0], [437.0, 1109.0], [62.0, 1109.0]], [[59.0, 1107.0], [472.0, 1108.0], [472.0, 1128.0], [59.0, 1127.0]]], "lines": ["●作品中の「トレバネーシコンパは極めて勉強な行為です。絶対に真似をしないでください。", "Ｗｉｎｄｏｗｓもこの作品はフィクションコンコは極めているようですが、です。実在する人物、団体、事件等といったので、に興味をしないことははー切関係ありません。", "●「週刊ビッグコミックスビリッツ「２０３０年１６－２０１３年１０－２６号掲載作品。", "きっとリビングコミンスピックの動けホムンクルス「公式ホームペ２０１５年１０月２４日木１１月２１日土日土曜日（土）日曜日）までのお"]}]}