{"version": "0.1.7", "img_width": 803, "img_height": 1200, "blocks": [{"box": [160, 93, 241, 219], "vertical": true, "font_size": 36, "lines_coords": [[[201.0, 93.0], [241.0, 93.0], [241.0, 165.0], [201.0, 165.0]], [[160.0, 96.0], [193.0, 96.0], [193.0, 219.0], [160.0, 219.0]]], "lines": ["あと", "もー少し"]}, {"box": [609, 351, 666, 416], "vertical": true, "font_size": 25, "lines_coords": [[[634.0, 351.0], [659.0, 351.0], [659.0, 416.0], [634.0, 416.0]], [[609.0, 351.0], [634.0, 351.0], [634.0, 416.0], [609.0, 416.0]]], "lines": ["楽しみ", "だなぁ"]}, {"box": [147, 363, 192, 421], "vertical": true, "font_size": 45, "lines_coords": [[[147.0, 363.0], [192.0, 363.0], [192.0, 421.0], [147.0, 421.0]]], "lines": ["映画"]}, {"box": [684, 713, 730, 808], "vertical": true, "font_size": 39, "lines_coords": [[[684.0, 713.0], [723.0, 713.0], [723.0, 808.0], [684.0, 808.0]]], "lines": ["高めろ"]}, {"box": [597, 849, 644, 945], "vertical": true, "font_size": 36, "lines_coords": [[[600.0, 851.0], [635.0, 853.0], [633.0, 944.0], [597.0, 943.0]]], "lines": ["自分を"]}, {"box": [295, 849, 341, 1031], "vertical": true, "font_size": 33, "lines_coords": [[[298.0, 849.0], [331.0, 849.0], [331.0, 1031.0], [298.0, 1031.0]]], "lines": ["変わり続けろ"]}, {"box": [110, 896, 199, 1081], "vertical": true, "font_size": 35, "lines_coords": [[[152.0, 898.0], [188.0, 897.0], [194.0, 1080.0], [158.0, 1081.0]], [[110.0, 896.0], [144.0, 896.0], [146.0, 1052.0], [112.0, 1052.0]]], "lines": ["この先ずっと", "変わらずに"]}]}