{"version": "0.1.7", "img_width": 803, "img_height": 1200, "blocks": [{"box": [671, 122, 760, 251], "vertical": true, "font_size": 89, "lines_coords": [[[671.0, 122.0], [760.0, 122.0], [760.0, 251.0], [671.0, 251.0]]], "lines": ["ようやくやろっとこれが"]}, {"box": [453, 112, 514, 183], "vertical": true, "font_size": 34, "lines_coords": [[[480.0, 113.0], [514.0, 113.0], [514.0, 142.0], [480.0, 142.0]], [[453.0, 112.0], [488.0, 112.0], [488.0, 183.0], [453.0, 183.0]]], "lines": ["あ", "島田．．．"]}, {"box": [43, 104, 368, 198], "vertical": false, "font_size": 64, "lines_coords": [[[46.0, 104.0], [331.0, 104.0], [331.0, 157.0], [46.0, 157.0]], [[43.0, 124.0], [368.0, 124.0], [368.0, 198.0], [43.0, 198.0]]], "lines": ["試作品出来たけど", "試作両立来だけどどこに送ればいい？"]}, {"box": [316, 271, 380, 330], "vertical": true, "font_size": 38, "lines_coords": [[[337.0, 271.0], [380.0, 271.0], [380.0, 330.0], [337.0, 330.0]], [[316.0, 274.0], [348.0, 274.0], [348.0, 328.0], [316.0, 328.0]]], "lines": ["忘れ", "てた"]}, {"box": [296, 377, 390, 481], "vertical": true, "font_size": 18, "lines_coords": [[[362.0, 377.0], [382.0, 377.0], [382.0, 464.0], [362.0, 464.0]], [[342.0, 378.0], [362.0, 378.0], [362.0, 474.0], [342.0, 474.0]], [[323.0, 379.0], [339.0, 379.0], [339.0, 481.0], [323.0, 481.0]], [[296.0, 378.0], [312.0, 378.0], [312.0, 462.0], [296.0, 462.0]]], "lines": ["面倒くさい", "なーこんな", "クソみたいな", "映画の為に"]}, {"box": [31, 412, 126, 510], "vertical": true, "font_size": 24, "lines_coords": [[[106.0, 416.0], [126.0, 416.0], [126.0, 510.0], [106.0, 510.0]], [[77.0, 412.0], [110.0, 412.0], [110.0, 460.0], [77.0, 460.0]], [[55.0, 414.0], [76.0, 414.0], [76.0, 489.0], [55.0, 489.0]], [[31.0, 414.0], [51.0, 414.0], [51.0, 491.0], [31.0, 491.0]]], "lines": ["なくなった", "って", "言っちゃ", "おうかな"]}, {"box": [540, 1020, 747, 1082], "vertical": false, "font_size": 59, "lines_coords": [[[540.0, 1024.0], [746.0, 1020.0], [747.0, 1079.0], [541.0, 1082.0]]], "lines": ["広瀬啓祐"]}, {"box": [44, 1011, 78, 1120], "vertical": true, "font_size": 34, "lines_coords": [[[44.0, 1012.0], [78.0, 1012.0], [78.0, 1120.0], [44.0, 1120.0]]], "lines": ["え．．．"]}]}