{"version": "0.1.6", "img_width": 847, "img_height": 1200, "blocks": [{"box": [718, 68, 739, 162], "vertical": true, "font_size": 16.0, "lines": ["わかった！？"]}, {"box": [376, 66, 429, 130], "vertical": true, "font_size": 27.0, "lines": ["あ．．．", "うん？"]}, {"box": [93, 69, 145, 176], "vertical": true, "font_size": 23.0, "lines": ["そう、", "よかったわ"]}, {"box": [633, 468, 708, 585], "vertical": true, "font_size": 20.0, "lines": ["それで？", "ほしいもの", "わかんない？"]}, {"box": [530, 469, 576, 584], "vertical": true, "font_size": 20.0, "lines": ["仲いいでしょ", "あなたたち。"]}, {"box": [233, 479, 251, 556], "vertical": true, "font_size": 16.0, "lines": ["えっと．．．"]}, {"box": [695, 878, 747, 1017], "vertical": true, "font_size": 25.0, "lines": ["他の女子から", "聞いたんだけど、"]}, {"box": [543, 853, 656, 1030], "vertical": true, "font_size": 25.0, "lines": ["北条、最近", "クッキー作りに", "ハマってるらしいん", "だよな．．．"]}, {"box": [134, 881, 240, 999], "vertical": true, "font_size": 22.0, "lines": ["あいつ料理", "苦手だから", "絶対マズいん", "だろうけど。"]}]}