{"version": "0.1.6", "img_width": 847, "img_height": 1200, "blocks": [{"box": [705, 49, 753, 222], "vertical": true, "font_size": 16.0, "lines": ["そ．．．それで高木さんは", "なんの用だったの．．．？"]}, {"box": [374, 85, 429, 180], "vertical": true, "font_size": 20.0, "lines": ["西片からで", "いいよ。"]}, {"box": [92, 97, 125, 145], "vertical": true, "font_size": 32.0, "lines": ["何？"]}, {"box": [672, 540, 698, 604], "vertical": true, "font_size": 26.0, "lines": ["では．．．"]}, {"box": [187, 558, 260, 594], "vertical": false, "font_size": 26.0, "lines": ["コホン"]}, {"box": [656, 775, 735, 931], "vertical": true, "font_size": 20.0, "lines": ["ウチの学校で", "近々けっこんする", "先生がいます。"]}, {"box": [174, 812, 201, 917], "vertical": true, "font_size": 20.0, "lines": ["誰でしょう。"]}]}