{"version": "0.1.7", "img_width": 847, "img_height": 1200, "blocks": [{"box": [723, 132, 746, 190], "vertical": true, "font_size": 23, "lines_coords": [[[723.0, 132.0], [746.0, 132.0], [746.0, 189.0], [723.0, 189.0]]], "lines": ["ハァ．．．"]}, {"box": [511, 98, 563, 252], "vertical": true, "font_size": 24, "lines_coords": [[[534.0, 98.0], [563.0, 98.0], [563.0, 164.0], [534.0, 164.0]], [[511.0, 101.0], [531.0, 101.0], [531.0, 251.0], [511.0, 251.0]]], "lines": ["なんで", "マラソンなんて．．．"]}, {"box": [356, 99, 463, 271], "vertical": true, "font_size": 20, "lines_coords": [[[436.0, 100.0], [456.0, 100.0], [456.0, 235.0], [436.0, 235.0]], [[410.0, 100.0], [429.0, 100.0], [429.0, 271.0], [410.0, 271.0]], [[383.0, 100.0], [402.0, 100.0], [402.0, 254.0], [383.0, 254.0]], [[356.0, 99.0], [376.0, 99.0], [376.0, 203.0], [356.0, 203.0]]], "lines": ["日常で走ること", "なんてないってのに", "なんでこんなこと", "するんだよ。"]}, {"box": [80, 51, 373, 72], "vertical": false, "font_size": 20, "lines_coords": [[[80.0, 51.0], [373.0, 52.0], [373.0, 72.0], [80.0, 71.0]]], "lines": ["からかいと手の高ホさんは"]}, {"box": [133, 129, 155, 233], "vertical": true, "font_size": 20, "lines_coords": [[[133.0, 130.0], [153.0, 130.0], [153.0, 233.0], [133.0, 233.0]]], "lines": ["ホントにな。"]}, {"box": [255, 536, 339, 656], "vertical": true, "font_size": 25, "lines_coords": [[[315.0, 541.0], [339.0, 541.0], [339.0, 602.0], [315.0, 602.0]], [[290.0, 542.0], [311.0, 542.0], [311.0, 656.0], [290.0, 656.0]], [[255.0, 540.0], [285.0, 536.0], [292.0, 595.0], [262.0, 598.0]]], "lines": ["なんか", "やる気だなー", "西片。"]}, {"box": [672, 965, 699, 1037], "vertical": true, "font_size": 25, "lines_coords": [[[672.0, 966.0], [697.0, 965.0], [699.0, 1035.0], [674.0, 1037.0]]], "lines": ["ふふふ。"]}, {"box": [158, 976, 188, 1039], "vertical": true, "font_size": 25, "lines_coords": [[[158.0, 976.0], [183.0, 976.0], [183.0, 1039.0], [158.0, 1039.0]]], "lines": ["西片．．．"]}]}