{"version": "0.1.6", "img_width": 722, "img_height": 1024, "blocks": [{"box": [588, 95, 647, 197], "vertical": true, "font_size": 21, "lines_coords": [[[588.0, 97.0], [609.0, 97.0], [609.0, 197.0], [588.0, 197.0]]], "lines": ["もしかして"]}, {"box": [368, 113, 432, 255], "vertical": true, "font_size": 28, "lines_coords": [[[396.0, 113.0], [432.0, 113.0], [432.0, 168.0], [396.0, 168.0]], [[370.0, 118.0], [391.0, 118.0], [391.0, 255.0], [370.0, 255.0]]], "lines": ["意地", "はってるの！？"]}, {"box": [247, 81, 330, 216], "vertical": true, "font_size": 16, "lines_coords": [[[312.0, 82.0], [329.0, 82.0], [330.0, 216.0], [313.0, 216.0]], [[291.0, 81.0], [308.0, 81.0], [307.0, 203.0], [290.0, 203.0]], [[267.0, 82.0], [284.0, 82.0], [286.0, 188.0], [269.0, 188.0]], [[248.0, 85.0], [261.0, 85.0], [261.0, 172.0], [248.0, 172.0]]], "lines": ["このパラシュートを", "見せられなかった", "自分への戒めの", "つもりなの？"]}, {"box": [573, 407, 657, 508], "vertical": true, "font_size": 23, "lines_coords": [[[632.0, 407.0], [657.0, 407.0], [657.0, 471.0], [632.0, 471.0]], [[605.0, 409.0], [626.0, 409.0], [626.0, 488.0], [605.0, 488.0]], [[573.0, 408.0], [595.0, 408.0], [597.0, 508.0], [575.0, 508.0]]], "lines": ["そんな", "ちゃちな", "プライドは"]}, {"box": [265, 432, 290, 498], "vertical": true, "font_size": 17, "lines_coords": [[[265.0, 433.0], [282.0, 433.0], [282.0, 498.0], [265.0, 498.0]]], "lines": ["田中君！！"]}, {"box": [90, 293, 154, 399], "vertical": true, "font_size": 20, "lines_coords": [[[131.0, 293.0], [154.0, 293.0], [154.0, 343.0], [131.0, 343.0]], [[109.0, 294.0], [132.0, 294.0], [132.0, 344.0], [109.0, 344.0]], [[91.0, 295.0], [106.0, 295.0], [105.0, 399.0], [90.0, 399.0]]], "lines": ["それで", "意地を", "はっているの？"]}, {"box": [85, 453, 132, 521], "vertical": true, "font_size": 18, "lines_coords": [[[110.0, 454.0], [127.0, 454.0], [127.0, 521.0], [110.0, 521.0]], [[85.0, 455.0], [103.0, 455.0], [103.0, 506.0], [85.0, 506.0]]], "lines": ["聞こえて", "るの！？"]}, {"box": [329, 437, 403, 599], "vertical": true, "font_size": 28, "lines_coords": [[[367.0, 439.0], [395.0, 439.0], [395.0, 599.0], [367.0, 599.0]], [[329.0, 439.0], [357.0, 439.0], [357.0, 597.0], [329.0, 597.0]]], "lines": ["期末テストに", "とっときな！！！"]}]}