{"version": "0.1.6", "img_width": 1022, "img_height": 1502, "blocks": [{"box": [869, 120, 952, 281], "vertical": true, "font_size": 23.0, "lines": ["．．．とか、まー", "どーでも", "いいんだけど。"]}, {"box": [467, 112, 493, 222], "vertical": true, "font_size": 25.0, "lines": ["西山さん。"]}, {"box": [678, 384, 733, 545], "vertical": true, "font_size": 25.0, "lines": ["くそう、西日が", "まぶしいぜ。"]}, {"box": [429, 444, 457, 544], "vertical": true, "font_size": 27.0, "lines": ["はいっ！？"]}, {"box": [530, 643, 585, 825], "vertical": true, "font_size": 25.0, "lines": ["世界はいつか", "終わるんだって。"]}, {"box": [891, 1059, 917, 1147], "vertical": true, "font_size": 26.0, "lines": ["はぁ！？"]}, {"box": [158, 1198, 283, 1243], "vertical": false, "font_size": 27.0, "lines": ["第３話ＩＤＰａ"]}]}