{"version": "0.1.7", "img_width": 850, "img_height": 1200, "blocks": [{"box": [691, 251, 729, 317], "vertical": true, "font_size": 38, "lines_coords": [[[691.0, 251.0], [729.0, 251.0], [729.0, 317.0], [691.0, 317.0]]], "lines": ["ボコ"]}, {"box": [487, 139, 514, 222], "vertical": true, "font_size": 25, "lines_coords": [[[487.0, 139.0], [512.0, 139.0], [512.0, 222.0], [487.0, 222.0]]], "lines": ["ボココ．．．"]}, {"box": [750, 452, 797, 527], "vertical": true, "font_size": 47, "lines_coords": [[[750.0, 452.0], [797.0, 452.0], [797.0, 527.0], [750.0, 527.0]]], "lines": ["ボコ"]}, {"box": [662, 695, 678, 793], "vertical": true, "font_size": 16, "lines_coords": [[[662.0, 695.0], [678.0, 695.0], [678.0, 793.0], [662.0, 793.0]]], "lines": ["．．．．．．"]}]}