{"version": "0.2.0-beta.6", "img_width": 835, "img_height": 1200, "blocks": [{"box": [666, 84, 715, 203], "vertical": true, "font_size": 20, "lines_coords": [[[695.0, 86.0], [715.0, 86.0], [715.0, 203.0], [695.0, 203.0]], [[666.0, 84.0], [686.0, 84.0], [686.0, 164.0], [666.0, 164.0]]], "lines": ["つーか、もう", "夏だよ！！"]}, {"box": [415, 75, 493, 234], "vertical": true, "font_size": 20, "lines_coords": [[[471.0, 75.0], [493.0, 75.0], [491.0, 233.0], [470.0, 233.0]], [[445.0, 76.0], [464.0, 76.0], [464.0, 230.0], [445.0, 230.0]], [[418.0, 77.0], [437.0, 77.0], [435.0, 203.0], [415.0, 203.0]]], "lines": ["そうやって俺達は", "確実に年をとって", "いくんだあぁー"]}, {"box": [80, 180, 102, 280], "vertical": true, "font_size": 20, "lines_coords": [[[80.0, 180.0], [100.0, 180.0], [100.0, 248.0], [80.0, 248.0]]], "lines": ["うえぇ"]}, {"box": [519, 353, 596, 509], "vertical": true, "font_size": 21, "lines_coords": [[[572.0, 353.0], [596.0, 353.0], [596.0, 509.0], [572.0, 509.0]], [[546.0, 355.0], [566.0, 355.0], [566.0, 455.0], [546.0, 455.0]], [[519.0, 353.0], [539.0, 353.0], [539.0, 492.0], [519.0, 492.0]]], "lines": ["今年はちょっぴり", "勇み足だぜ、", "夏さんよぉー！！"]}, {"box": [395, 326, 444, 445], "vertical": true, "font_size": 21, "lines_coords": [[[422.0, 326.0], [443.0, 326.0], [441.0, 442.0], [420.0, 442.0]], [[395.0, 329.0], [416.0, 329.0], [416.0, 411.0], [395.0, 411.0]]], "lines": ["．．．こんなこと", "言ったら、"]}, {"box": [300, 327, 349, 473], "vertical": true, "font_size": 20, "lines_coords": [[[326.0, 329.0], [347.0, 329.0], [347.0, 407.0], [326.0, 407.0]], [[300.0, 328.0], [320.0, 328.0], [320.0, 468.0], [300.0, 468.0]]], "lines": ["あの人は", "どう思うのかな。"]}, {"box": [162, 326, 240, 473], "vertical": true, "font_size": 22, "lines_coords": [[[215.0, 326.0], [240.0, 326.0], [240.0, 407.0], [215.0, 407.0]], [[192.0, 326.0], [213.0, 326.0], [210.0, 445.0], [189.0, 445.0]], [[163.0, 326.0], [183.0, 326.0], [182.0, 468.0], [162.0, 468.0]]], "lines": ["あたしは", "ちょっとだけ", "ごめんって思う。"]}, {"box": [651, 959, 672, 1026], "vertical": true, "font_size": 21, "lines_coords": [[[651.0, 960.0], [672.0, 960.0], [672.0, 1024.0], [651.0, 1024.0]]], "lines": ["．．．でも、"]}, {"box": [458, 958, 565, 1137], "vertical": true, "font_size": 25, "lines_coords": [[[536.0, 959.0], [565.0, 959.0], [565.0, 1028.0], [536.0, 1028.0]], [[509.0, 958.0], [539.0, 958.0], [539.0, 1028.0], [509.0, 1028.0]], [[484.0, 960.0], [505.0, 960.0], [507.0, 1135.0], [486.0, 1135.0]], [[460.0, 962.0], [480.0, 962.0], [480.0, 1099.0], [460.0, 1099.0]]], "lines": ["たとえ、", "いつか、", "この景色が見れなく", "なる時が来ても"]}, {"box": [271, 959, 377, 1135], "vertical": true, "font_size": 21, "lines_coords": [[[354.0, 959.0], [375.0, 959.0], [375.0, 1060.0], [354.0, 1060.0]], [[326.0, 960.0], [347.0, 960.0], [348.0, 1134.0], [327.0, 1134.0]], [[300.0, 960.0], [322.0, 960.0], [322.0, 1059.0], [300.0, 1059.0]], [[271.0, 959.0], [292.0, 959.0], [295.0, 1068.0], [274.0, 1068.0]]], "lines": ["その時まで", "みんなといっしょに", "いられれば", "それでいい。"]}, {"box": [170, 959, 192, 1106], "vertical": true, "font_size": 16, "lines_coords": [[[172.0, 964.0], [188.0, 964.0], [188.0, 1102.0], [172.0, 1102.0]]], "lines": ["今日はそう思う。"]}]}