{"version": "0.1.7", "img_width": 1119, "img_height": 1600, "blocks": [{"box": [465, 101, 492, 287], "vertical": true, "font_size": 20, "lines_coords": [[[467.0, 103.0], [487.0, 103.0], [487.0, 281.0], [467.0, 281.0]]], "lines": ["なんかヘンなの"]}, {"box": [296, 100, 417, 342], "vertical": true, "font_size": 26, "lines_coords": [[[390.0, 103.0], [417.0, 103.0], [417.0, 228.0], [390.0, 228.0]], [[357.0, 101.0], [386.0, 101.0], [387.0, 254.0], [359.0, 254.0]], [[331.0, 104.0], [353.0, 104.0], [353.0, 228.0], [331.0, 228.0]], [[296.0, 100.0], [323.0, 100.0], [325.0, 342.0], [298.0, 342.0]]], "lines": ["あと数年で", "ねーちゃんは", "お母さんを", "追い越しちゃうんだ。"]}, {"box": [167, 510, 229, 714], "vertical": true, "font_size": 30, "lines_coords": [[[201.0, 510.0], [228.0, 510.0], [226.0, 714.0], [200.0, 714.0]], [[167.0, 510.0], [200.0, 510.0], [200.0, 600.0], [167.0, 600.0]]], "lines": ["：：：ねーちゃんも", "大変だ。"]}, {"box": [756, 1264, 782, 1415], "vertical": true, "font_size": 22, "lines_coords": [[[757.0, 1267.0], [779.0, 1267.0], [779.0, 1409.0], [757.0, 1409.0]]], "lines": ["蒸し暑い．．．"]}, {"box": [595, 1262, 684, 1518], "vertical": true, "font_size": 25, "lines_coords": [[[656.0, 1264.0], [684.0, 1264.0], [684.0, 1365.0], [656.0, 1365.0]], [[625.0, 1262.0], [651.0, 1262.0], [651.0, 1439.0], [625.0, 1439.0]], [[595.0, 1264.0], [617.0, 1264.0], [617.0, 1514.0], [595.0, 1514.0]]], "lines": ["なんだか", "心も体も空気に", "溶けちゃうような．．．"]}, {"box": [185, 1264, 309, 1454], "vertical": true, "font_size": 28, "lines_coords": [[[281.0, 1265.0], [307.0, 1265.0], [307.0, 1453.0], [281.0, 1453.0]], [[246.0, 1265.0], [275.0, 1265.0], [275.0, 1400.0], [246.0, 1400.0]], [[214.0, 1264.0], [242.0, 1264.0], [245.0, 1401.0], [217.0, 1401.0]], [[185.0, 1265.0], [212.0, 1265.0], [212.0, 1398.0], [185.0, 1398.0]]], "lines": ["ああ、ごめん．．．", "ねーちゃん、", "あたしは今、", "腐ってます。"]}]}