{"version": "0.1.6", "img_width": 980, "img_height": 1399, "blocks": [{"box": [647, 86, 667, 161], "vertical": true, "font_size": 19.0, "lines": ["ん．．．"]}, {"box": [530, 88, 608, 292], "vertical": true, "font_size": 19.0, "lines": ["鈴木くんが入らない", "ほうがいいと思うなら、", "仕方ないけれど、"]}, {"box": [77, 217, 161, 403], "vertical": true, "font_size": 21.0, "lines": ["見学でもいいから", "できるだけ学校には", "来てほしいな。"]}, {"box": [501, 985, 565, 1051], "vertical": true, "font_size": 32.0, "lines": ["まあ"]}, {"box": [378, 990, 433, 1050], "vertical": true, "font_size": 32.0, "lines": ["っ"]}, {"box": [179, 759, 209, 834], "vertical": true, "font_size": 30.0, "lines": ["．．．ハイ。"]}, {"box": [853, 1140, 912, 1269], "vertical": true, "font_size": 32.0, "lines": ["．．．"]}, {"box": [370, 1185, 685, 1330], "vertical": false, "font_size": 32.0, "lines": ["着がえたら", "ゴールに集合"]}]}