{"version": "0.1.7", "img_width": 850, "img_height": 1200, "blocks": [{"box": [772, 53, 793, 117], "vertical": true, "font_size": 21, "lines_coords": [[[772.0, 53.0], [793.0, 53.0], [793.0, 117.0], [772.0, 117.0]]], "lines": ["ぬお．．．"]}, {"box": [565, 60, 589, 121], "vertical": true, "font_size": 24, "lines_coords": [[[565.0, 60.0], [589.0, 60.0], [589.0, 121.0], [565.0, 121.0]]], "lines": ["ち．．．．．"]}, {"box": [243, 342, 300, 473], "vertical": true, "font_size": 29, "lines_coords": [[[267.0, 342.0], [300.0, 342.0], [300.0, 392.0], [267.0, 392.0]], [[243.0, 342.0], [268.0, 342.0], [272.0, 473.0], [247.0, 473.0]]], "lines": ["力が", "入らねェ．．．"]}, {"box": [461, 653, 552, 850], "vertical": true, "font_size": 78, "lines_coords": [[[461.0, 658.0], [539.0, 653.0], [552.0, 846.0], [474.0, 850.0]]], "lines": ["おいっ。"]}, {"box": [414, 944, 435, 996], "vertical": true, "font_size": 21, "lines_coords": [[[414.0, 944.0], [435.0, 944.0], [435.0, 996.0], [414.0, 996.0]]], "lines": ["！"]}]}