{"version": "0.1.7", "img_width": 1040, "img_height": 1592, "blocks": [{"box": [362, 157, 438, 275], "vertical": true, "font_size": 32, "lines_coords": [[[399.0, 157.0], [438.0, 158.0], [435.0, 251.0], [396.0, 250.0]], [[362.0, 163.0], [390.0, 163.0], [390.0, 275.0], [362.0, 275.0]]], "lines": ["白黒に", "無声か．．"]}, {"box": [293, 279, 359, 394], "vertical": true, "font_size": 32, "lines_coords": [[[321.0, 279.0], [355.0, 279.0], [359.0, 394.0], [324.0, 394.0]], [[293.0, 281.0], [321.0, 281.0], [321.0, 365.0], [293.0, 365.0]]], "lines": ["昔の映画", "みたい"]}, {"box": [893, 785, 999, 942], "vertical": true, "font_size": 27, "lines_coords": [[[966.0, 785.0], [999.0, 785.0], [999.0, 892.0], [966.0, 892.0]], [[931.0, 786.0], [957.0, 786.0], [957.0, 942.0], [931.0, 942.0]], [[893.0, 786.0], [920.0, 786.0], [920.0, 942.0], [893.0, 942.0]]], "lines": ["てか全然", "映画の雰囲気", "変えてきたな"]}, {"box": [781, 856, 875, 995], "vertical": true, "font_size": 27, "lines_coords": [[[848.0, 856.0], [875.0, 856.0], [875.0, 995.0], [848.0, 995.0]], [[806.0, 856.0], [833.0, 856.0], [837.0, 984.0], [811.0, 984.0]], [[781.0, 859.0], [803.0, 859.0], [803.0, 985.0], [781.0, 985.0]]], "lines": ["まぁあれは", "現実的じゃ", "なかったし"]}, {"box": [217, 1522, 317, 1554], "vertical": false, "font_size": 28, "lines_coords": [[[217.0, 1526.0], [315.0, 1522.0], [317.0, 1550.0], [219.0, 1554.0]]], "lines": ["あなた"]}]}