{"version": "0.1.6", "img_width": 1354, "img_height": 1920, "blocks": [{"box": [1136, 108, 1260, 264], "vertical": true, "font_size": 32.0, "lines": ["さっさと", "食べなさい", "よ！！"]}, {"box": [755, 114, 842, 288], "vertical": true, "font_size": 32.0, "lines": ["手が", "疲れるのよ。"]}, {"box": [399, 116, 450, 204], "vertical": true, "font_size": 32.0, "lines": ["もが。"]}, {"box": [1112, 967, 1181, 1136], "vertical": true, "font_size": 30.0, "lines": ["ほら！！", "もう行って！！"]}, {"box": [917, 986, 1023, 1179], "vertical": true, "font_size": 30.0, "lines": ["私がこんな", "恰好してたって", "言わないでよ。"]}, {"box": [343, 969, 386, 1085], "vertical": true, "font_size": 32.0, "lines": ["あ、あぁ。"]}, {"box": [225, 1012, 290, 1190], "vertical": true, "font_size": 32.0, "lines": ["ありがとな", "ごちそーさま。"]}]}