{"version": "0.2.0-beta.6", "img_width": 1450, "img_height": 2120, "blocks": [{"box": [240, 279, 356, 407], "vertical": false, "font_size": 38, "lines_coords": [[[258.0, 317.0], [308.0, 317.0], [308.0, 338.0], [258.0, 338.0]], [[252.0, 334.0], [331.0, 334.0], [331.0, 361.0], [252.0, 361.0]], [[240.0, 336.0], [339.0, 336.0], [339.0, 410.0], [240.0, 410.0]]], "lines": ["貴様はねえみえええん？もそれの時子供のカップルですか？", "おまえもちょっということもありますほどのままでしておいしょうかもしれませんが．．．わからなかったのだからこれから", "わーっとしてくださいっているのですから、それはそうだったのだろうなんでしょうがないのかなんだかわからなかったんですが．．．ありがとうございませんかないですね。"]}, {"box": [488, 279, 602, 399], "vertical": false, "font_size": 21, "lines_coords": [[[493.0, 285.0], [575.0, 279.0], [577.0, 308.0], [495.0, 314.0]], [[505.0, 306.0], [573.0, 306.0], [573.0, 327.0], [505.0, 327.0]], [[503.0, 322.0], [588.0, 316.0], [590.0, 339.0], [505.0, 345.0]], [[499.0, 341.0], [592.0, 335.0], [594.0, 358.0], [501.0, 364.0]], [[495.0, 360.0], [573.0, 360.0], [573.0, 380.0], [495.0, 380.0]], [[499.0, 380.0], [546.0, 380.0], [546.0, 389.0], [499.0, 389.0]]], "lines": ["いろいろ勝ちだ", "『私は見てて", "前回はいかにして", "や．．．あのうじゃ", "できますようお", "．．．"]}, {"box": [515, 434, 590, 457], "vertical": false, "font_size": 23, "lines_coords": [[[515.0, 434.0], [590.0, 434.0], [590.0, 457.0], [515.0, 457.0]]], "lines": ["邦外よ！！"]}, {"box": [855, 278, 990, 339], "vertical": false, "font_size": 28, "lines_coords": [[[859.0, 281.0], [979.0, 279.0], [979.0, 306.0], [859.0, 308.0]], [[867.0, 308.0], [981.0, 302.0], [983.0, 335.0], [870.0, 341.0]]], "lines": ["確かにバカっていたで", "悪いの事実だければいいの"]}, {"box": [455, 708, 977, 891], "vertical": false, "font_size": 82, "lines_coords": [[[455.0, 745.0], [799.0, 708.0], [807.0, 795.0], [464.0, 832.0]], [[509.0, 813.0], [894.0, 805.0], [896.0, 881.0], [511.0, 890.0]]], "lines": ["ニュームサイの", "来年もおに来まーで"]}, {"box": [553, 906, 903, 1010], "vertical": false, "font_size": 34.666666666666664, "lines_coords": [[[553.0, 915.0], [903.0, 906.0], [903.0, 956.0], [553.0, 964.0]], [[582.0, 950.0], [627.0, 950.0], [627.0, 975.0], [582.0, 975.0]], [[557.0, 981.0], [642.0, 977.0], [644.0, 1006.0], [559.0, 1010.0]]], "lines": ["ちゃぁーやういみあった", "やれやれ", "都道府県"]}]}